{
  "status": "OPTIMAL_SOLUTION",
  "solution": {
    "objective": 9537,
    "start_time": [
      [
        43,
        549,
        261,
        784,
        875,
        795,
        362,
        565,
        450,
        278,
        704,
        21,
        194
      ],
      [
        230,
        454,
        317,
        870,
        373,
        560,
        179,
        704,
        549,
        765,
        639,
        252,
        924
      ],
      [
        639,
        945,
        445,
        567,
        710,
        875,
        230,
        0,
        815,
        77,
        300,
        342,
        28
      ],
      [
        710,
        835,
        158,
        663,
        433,
        362,
        311,
        28,
        639,
        602,
        528,
        228,
        808
      ],
      [
        0,
        565,
        648,
        687,
        179,
        197,
        127,
        838,
        294,
        438,
        425,
        43,
        78
      ],
      [
        160,
        257,
        563,
        277,
        127,
        713,
        67,
        415,
        358,
        142,
        196,
        470,
        614
      ],
      [
        567,
        433,
        666,
        531,
        407,
        945,
        300,
        323,
        34,
        830,
        0,
        740,
        98
      ],
      [
        840,
        176,
        95,
        470,
        639,
        0,
        790,
        237,
        567,
        531,
        342,
        425,
        701
      ],
      [
        872,
        277,
        373,
        795,
        67,
        445,
        0,
        935,
        663,
        567,
        122,
        159,
        578
      ],
      [
        934,
        0,
        610,
        48,
        749,
        294,
        549,
        152,
        84,
        701,
        438,
        816,
        652
      ],
      [
        289,
        94,
        21,
        989,
        197,
        639,
        450,
        815,
        727,
        578,
        924,
        0,
        838
      ]
    ],
    "SpeedScaling": [
      [
        1,
        1,
        1,
        1,
        1,
        1,
        1,
        1,
        1,
        1,
        1,
        1,
        1
      ],
      [
        1,
        1,
        1,
        1,
        1,
        1,
        1,
        1,
        1,
        1,
        1,
        1,
        1
      ],
      [
        1,
        1,
        1,
        1,
        1,
        1,
        1,
        1,
        1,
        1,
        1,
        1,
        1
      ],
      [
        1,
        1,
        1,
        1,
        1,
        1,
        1,
        1,
        1,
        1,
        1,
        1,
        1
      ],
      [
        1,
        1,
        1,
        1,
        1,
        1,
        1,
        1,
        1,
        1,
        1,
        1,
        1
      ],
      [
        1,
        1,
        1,
        1,
        1,
        1,
        1,
        1,
        1,
        1,
        1,
        1,
        1
      ],
      [
        1,
        1,
        1,
        1,
        1,
        1,
        1,
        1,
        1,
        1,
        1,
        1,
        1
      ],
      [
        1,
        1,
        1,
        1,
        1,
        1,
        1,
        1,
        1,
        1,
        1,
        1,
        1
      ],
      [
        1,
        1,
        1,
        1,
        1,
        1,
        1,
        1,
        1,
        1,
        1,
        1,
        1
      ],
      [
        1,
        1,
        1,
        1,
        1,
        1,
        1,
        1,
        1,
        1,
        1,
        1,
        1
      ],
      [
        1,
        1,
        1,
        1,
        1,
        1,
        1,
        1,
        1,
        1,
        1,
        1,
        1
      ]
    ],
    "_output_item": "Objective function: 1018 + 8519 = 9537 \nStart Times: [43, 549, 261, 784, 875, 795, 362, 565, 450, 278, 704, 21, 194, 230, 454, 317, 870, 373, 560, 179, 704, 549, 765, 639, 252, 924, 639, 945, 445, 567, 710, 875, 230, 0, 815, 77, 300, 342, 28, 710, 835, 158, 663, 433, 362, 311, 28, 639, 602, 528, 228, 808, 0, 565, 648, 687, 179, 197, 127, 838, 294, 438, 425, 43, 78, 160, 257, 563, 277, 127, 713, 67, 415, 358, 142, 196, 470, 614, 567, 433, 666, 531, 407, 945, 300, 323, 34, 830, 0, 740, 98, 840, 176, 95, 470, 639, 0, 790, 237, 567, 531, 342, 425, 701, 872, 277, 373, 795, 67, 445, 0, 935, 663, 567, 122, 159, 578, 934, 0, 610, 48, 749, 294, 549, 152, 84, 701, 438, 816, 652, 289, 94, 21, 989, 197, 639, 450, 815, 727, 578, 924, 0, 838]\nSpeed Scaling; [1, 1, 1, 1, 1, 1, 1, 1, 1, 1, 1, 1, 1, 1, 1, 1, 1, 1, 1, 1, 1, 1, 1, 1, 1, 1, 1, 1, 1, 1, 1, 1, 1, 1, 1, 1, 1, 1, 1, 1, 1, 1, 1, 1, 1, 1, 1, 1, 1, 1, 1, 1, 1, 1, 1, 1, 1, 1, 1, 1, 1, 1, 1, 1, 1, 1, 1, 1, 1, 1, 1, 1, 1, 1, 1, 1, 1, 1, 1, 1, 1, 1, 1, 1, 1, 1, 1, 1, 1, 1, 1, 1, 1, 1, 1, 1, 1, 1, 1, 1, 1, 1, 1, 1, 1, 1, 1, 1, 1, 1, 1, 1, 1, 1, 1, 1, 1, 1, 1, 1, 1, 1, 1, 1, 1, 1, 1, 1, 1, 1, 1, 1, 1, 1, 1, 1, 1, 1, 1, 1, 1, 1, 1]\n",
    "_checker": ""
  },
  "statistics": {
    "paths": 0,
    "flatBoolVars": 1430,
    "flatIntVars": 288,
    "flatBoolConstraints": 715,
    "flatIntConstraints": 2433,
    "evaluatedHalfReifiedConstraints": 1430,
    "method": "minimize",
    "flatTime": 99.705,
    "objective": 9537,
    "objectiveBound": 9537,
    "boolVariables": 715,
    "failures": 0,
    "propagations": 19988,
    "solveTime": 509.609,
    "time": 573.0,
    "nSolutions": 92,
    "maxTime": 72304,
    "makespan": 1018.0,
    "energy": 8519.0
  }
}