{
  "status": "SATISFIED",
  "solution": {
    "objective": 17224,
    "start_time": [
      [
        0,
        846,
        61,
        77,
        1086,
        133,
        618,
        698,
        1118,
        230,
        946,
        383
      ],
      [
        61,
        1203,
        84,
        1012,
        141,
        963,
        0,
        1337,
        197,
        311,
        276,
        463
      ],
      [
        310,
        496,
        175,
        941,
        799,
        375,
        33,
        153,
        871,
        424,
        125,
        269
      ],
      [
        1160,
        25,
        979,
        240,
        1315,
        944,
        590,
        920,
        1050,
        556,
        1206,
        1284
      ],
      [
        156,
        1012,
        1040,
        1256,
        0,
        90,
        501,
        233,
        645,
        1312,
        1109,
        181
      ],
      [
        1027,
        1270,
        825,
        419,
        474,
        217,
        330,
        1007,
        941,
        372,
        1359,
        1134
      ],
      [
        180,
        678,
        1170,
        1355,
        711,
        424,
        105,
        599,
        800,
        971,
        240,
        143
      ],
      [
        660,
        790,
        331,
        1345,
        589,
        1010,
        254,
        415,
        730,
        1133,
        801,
        528
      ],
      [
        722,
        320,
        415,
        1107,
        889,
        645,
        1021,
        844,
        556,
        494,
        0,
        772
      ],
      [
        869,
        190,
        526,
        1278,
        961,
        1081,
        698,
        1145,
        121,
        1045,
        622,
        724
      ],
      [
        752,
        88,
        1109,
        1193,
        27,
        237,
        366,
        786,
        438,
        588,
        1299,
        634
      ],
      [
        375,
        939,
        1227,
        599,
        1012,
        746,
        478,
        511,
        97,
        1246,
        457,
        1315
      ],
      [
        483,
        1031,
        901,
        580,
        1171,
        847,
        709,
        1243,
        0,
        1330,
        565,
        1092
      ],
      [
        81,
        0,
        713,
        316,
        772,
        305,
        940,
        1111,
        330,
        822,
        1031,
        233
      ],
      [
        1136,
        561,
        465,
        38,
        263,
        681,
        882,
        944,
        1216,
        0,
        1374,
        844
      ],
      [
        457,
        1092,
        1246,
        526,
        660,
        605,
        143,
        1186,
        762,
        158,
        483,
        934
      ],
      [
        1124,
        1186,
        1322,
        698,
        357,
        0,
        783,
        669,
        979,
        1081,
        935,
        1206
      ],
      [
        1198,
        634,
        269,
        94,
        197,
        517,
        434,
        0,
        822,
        727,
        864,
        605
      ],
      [
        774,
        245,
        947,
        1373,
        1245,
        1402,
        1301,
        1063,
        1329,
        1194,
        997,
        872
      ],
      [
        565,
        825,
        769,
        871,
        1097,
        1299,
        1344,
        892,
        848,
        918,
        1257,
        973
      ],
      [
        944,
        713,
        622,
        1402,
        415,
        1145,
        158,
        1027,
        1291,
        1114,
        1348,
        290
      ],
      [
        240,
        1334,
        140,
        178,
        125,
        1209,
        1104,
        310,
        398,
        631,
        95,
        0
      ]
    ],
    "SpeedScaling": [
      [
        1,
        1,
        1,
        1,
        1,
        1,
        1,
        1,
        1,
        1,
        1,
        1
      ],
      [
        1,
        1,
        1,
        1,
        1,
        1,
        1,
        1,
        1,
        1,
        1,
        1
      ],
      [
        1,
        1,
        1,
        1,
        1,
        1,
        1,
        1,
        1,
        1,
        1,
        1
      ],
      [
        1,
        1,
        1,
        1,
        1,
        1,
        1,
        1,
        1,
        1,
        1,
        1
      ],
      [
        1,
        1,
        1,
        1,
        1,
        1,
        1,
        1,
        1,
        1,
        1,
        1
      ],
      [
        1,
        1,
        1,
        1,
        1,
        1,
        1,
        1,
        1,
        1,
        1,
        1
      ],
      [
        1,
        1,
        1,
        1,
        1,
        1,
        1,
        1,
        1,
        1,
        1,
        1
      ],
      [
        1,
        1,
        1,
        1,
        1,
        1,
        1,
        1,
        1,
        1,
        1,
        1
      ],
      [
        1,
        1,
        1,
        1,
        1,
        1,
        1,
        1,
        1,
        1,
        1,
        1
      ],
      [
        1,
        1,
        1,
        1,
        1,
        1,
        1,
        1,
        1,
        1,
        1,
        1
      ],
      [
        1,
        1,
        1,
        1,
        1,
        1,
        1,
        1,
        1,
        1,
        1,
        1
      ],
      [
        1,
        1,
        1,
        1,
        1,
        1,
        1,
        1,
        1,
        1,
        1,
        1
      ],
      [
        1,
        1,
        1,
        1,
        1,
        1,
        1,
        1,
        1,
        1,
        1,
        1
      ],
      [
        1,
        1,
        1,
        1,
        1,
        1,
        1,
        1,
        1,
        1,
        1,
        1
      ],
      [
        1,
        1,
        1,
        1,
        1,
        1,
        1,
        1,
        1,
        1,
        1,
        1
      ],
      [
        1,
        1,
        1,
        1,
        1,
        1,
        1,
        1,
        1,
        1,
        1,
        1
      ],
      [
        1,
        1,
        1,
        1,
        1,
        1,
        1,
        1,
        1,
        1,
        1,
        1
      ],
      [
        1,
        1,
        1,
        1,
        1,
        1,
        1,
        1,
        1,
        1,
        1,
        1
      ],
      [
        1,
        1,
        1,
        1,
        1,
        1,
        1,
        1,
        1,
        1,
        1,
        1
      ],
      [
        1,
        1,
        1,
        1,
        1,
        1,
        1,
        1,
        1,
        1,
        1,
        1
      ],
      [
        1,
        1,
        1,
        1,
        1,
        1,
        1,
        1,
        1,
        1,
        1,
        1
      ],
      [
        1,
        1,
        1,
        1,
        1,
        1,
        1,
        1,
        1,
        1,
        1,
        1
      ]
    ],
    "_output_item": "Objective function: 1419 + 15805 = 17224 \nStart Times: [0, 846, 61, 77, 1086, 133, 618, 698, 1118, 230, 946, 383, 61, 1203, 84, 1012, 141, 963, 0, 1337, 197, 311, 276, 463, 310, 496, 175, 941, 799, 375, 33, 153, 871, 424, 125, 269, 1160, 25, 979, 240, 1315, 944, 590, 920, 1050, 556, 1206, 1284, 156, 1012, 1040, 1256, 0, 90, 501, 233, 645, 1312, 1109, 181, 1027, 1270, 825, 419, 474, 217, 330, 1007, 941, 372, 1359, 1134, 180, 678, 1170, 1355, 711, 424, 105, 599, 800, 971, 240, 143, 660, 790, 331, 1345, 589, 1010, 254, 415, 730, 1133, 801, 528, 722, 320, 415, 1107, 889, 645, 1021, 844, 556, 494, 0, 772, 869, 190, 526, 1278, 961, 1081, 698, 1145, 121, 1045, 622, 724, 752, 88, 1109, 1193, 27, 237, 366, 786, 438, 588, 1299, 634, 375, 939, 1227, 599, 1012, 746, 478, 511, 97, 1246, 457, 1315, 483, 1031, 901, 580, 1171, 847, 709, 1243, 0, 1330, 565, 1092, 81, 0, 713, 316, 772, 305, 940, 1111, 330, 822, 1031, 233, 1136, 561, 465, 38, 263, 681, 882, 944, 1216, 0, 1374, 844, 457, 1092, 1246, 526, 660, 605, 143, 1186, 762, 158, 483, 934, 1124, 1186, 1322, 698, 357, 0, 783, 669, 979, 1081, 935, 1206, 1198, 634, 269, 94, 197, 517, 434, 0, 822, 727, 864, 605, 774, 245, 947, 1373, 1245, 1402, 1301, 1063, 1329, 1194, 997, 872, 565, 825, 769, 871, 1097, 1299, 1344, 892, 848, 918, 1257, 973, 944, 713, 622, 1402, 415, 1145, 158, 1027, 1291, 1114, 1348, 290, 240, 1334, 140, 178, 125, 1209, 1104, 310, 398, 631, 95, 0]\nSpeed Scaling; [1, 1, 1, 1, 1, 1, 1, 1, 1, 1, 1, 1, 1, 1, 1, 1, 1, 1, 1, 1, 1, 1, 1, 1, 1, 1, 1, 1, 1, 1, 1, 1, 1, 1, 1, 1, 1, 1, 1, 1, 1, 1, 1, 1, 1, 1, 1, 1, 1, 1, 1, 1, 1, 1, 1, 1, 1, 1, 1, 1, 1, 1, 1, 1, 1, 1, 1, 1, 1, 1, 1, 1, 1, 1, 1, 1, 1, 1, 1, 1, 1, 1, 1, 1, 1, 1, 1, 1, 1, 1, 1, 1, 1, 1, 1, 1, 1, 1, 1, 1, 1, 1, 1, 1, 1, 1, 1, 1, 1, 1, 1, 1, 1, 1, 1, 1, 1, 1, 1, 1, 1, 1, 1, 1, 1, 1, 1, 1, 1, 1, 1, 1, 1, 1, 1, 1, 1, 1, 1, 1, 1, 1, 1, 1, 1, 1, 1, 1, 1, 1, 1, 1, 1, 1, 1, 1, 1, 1, 1, 1, 1, 1, 1, 1, 1, 1, 1, 1, 1, 1, 1, 1, 1, 1, 1, 1, 1, 1, 1, 1, 1, 1, 1, 1, 1, 1, 1, 1, 1, 1, 1, 1, 1, 1, 1, 1, 1, 1, 1, 1, 1, 1, 1, 1, 1, 1, 1, 1, 1, 1, 1, 1, 1, 1, 1, 1, 1, 1, 1, 1, 1, 1, 1, 1, 1, 1, 1, 1, 1, 1, 1, 1, 1, 1, 1, 1, 1, 1, 1, 1, 1, 1, 1, 1, 1, 1, 1, 1, 1, 1, 1, 1, 1, 1, 1, 1, 1, 1, 1, 1, 1, 1, 1, 1]\n",
    "_checker": ""
  },
  "statistics": {
    "paths": 0,
    "flatBoolVars": 5544,
    "flatIntVars": 530,
    "flatBoolConstraints": 2772,
    "flatIntConstraints": 7262,
    "evaluatedHalfReifiedConstraints": 5544,
    "method": "minimize",
    "flatTime": 222.958,
    "objective": 17224,
    "objectiveBound": 16741,
    "boolVariables": 2772,
    "failures": 0,
    "propagations": 182889,
    "solveTime": 25605.6,
    "time": 25969.0,
    "nSolutions": 281,
    "maxTime": 102263,
    "makespan": 1419.0,
    "energy": 15805.0
  }
}