{
  "status": "SATISFIED",
  "solution": {
    "objective": 12894,
    "start_time": [
      [
        0,
        266,
        844,
        403,
        607,
        310,
        925,
        153
      ],
      [
        134,
        491,
        165,
        45,
        253,
        855,
        700,
        620
      ],
      [
        99,
        1011,
        76,
        1114,
        829,
        246,
        362,
        395
      ],
      [
        1360,
        784,
        1155,
        882,
        970,
        1053,
        1257,
        1186
      ],
      [
        902,
        442,
        306,
        1209,
        1280,
        176,
        944,
        491
      ],
      [
        1114,
        742,
        245,
        1065,
        375,
        836,
        1152,
        945
      ],
      [
        752,
        1328,
        98,
        221,
        351,
        157,
        257,
        52
      ],
      [
        1152,
        1360,
        1009,
        133,
        885,
        403,
        534,
        0
      ],
      [
        449,
        378,
        764,
        869,
        548,
        0,
        1100,
        700
      ],
      [
        1065,
        630,
        149,
        796,
        0,
        1306,
        999,
        1288
      ],
      [
        221,
        0,
        436,
        151,
        1259,
        482,
        326,
        1160
      ],
      [
        690,
        1403,
        925,
        1341,
        758,
        1144,
        1180,
        1048
      ],
      [
        417,
        93,
        1092,
        947,
        223,
        730,
        484,
        534
      ],
      [
        149,
        1162,
        1348,
        0,
        60,
        1198,
        395,
        720
      ],
      [
        1285,
        575,
        1187,
        1360,
        1035,
        630,
        246,
        969
      ],
      [
        621,
        1202,
        1283,
        731,
        1180,
        694,
        855,
        792
      ],
      [
        988,
        310,
        566,
        460,
        668,
        945,
        796,
        855
      ],
      [
        820,
        1089,
        474,
        524,
        149,
        20,
        223,
        1342
      ],
      [
        944,
        1263,
        1166,
        616,
        1350,
        421,
        172,
        1144
      ],
      [
        1180,
        938,
        690,
        252,
        1083,
        1339,
        988,
        1006
      ],
      [
        546,
        1238,
        634,
        779,
        1202,
        825,
        1351,
        1306
      ],
      [
        376,
        845,
        493,
        1053,
        583,
        988,
        631,
        1257
      ],
      [
        282,
        677,
        378,
        1224,
        473,
        565,
        751,
        125
      ],
      [
        1259,
        172,
        0,
        1287,
        1229,
        125,
        157,
        76
      ]
    ],
    "SpeedScaling": [
      [
        1,
        1,
        1,
        1,
        1,
        1,
        1,
        1
      ],
      [
        1,
        1,
        1,
        1,
        1,
        1,
        1,
        1
      ],
      [
        1,
        1,
        1,
        1,
        1,
        1,
        1,
        1
      ],
      [
        1,
        1,
        1,
        1,
        1,
        1,
        1,
        1
      ],
      [
        1,
        1,
        1,
        1,
        1,
        1,
        1,
        1
      ],
      [
        1,
        1,
        1,
        1,
        1,
        1,
        1,
        1
      ],
      [
        1,
        1,
        1,
        1,
        1,
        1,
        1,
        1
      ],
      [
        1,
        1,
        1,
        1,
        1,
        1,
        1,
        1
      ],
      [
        1,
        1,
        1,
        1,
        1,
        1,
        1,
        1
      ],
      [
        1,
        1,
        1,
        1,
        1,
        1,
        1,
        1
      ],
      [
        1,
        1,
        1,
        1,
        1,
        1,
        1,
        1
      ],
      [
        1,
        1,
        1,
        1,
        1,
        1,
        1,
        1
      ],
      [
        1,
        1,
        1,
        1,
        1,
        1,
        1,
        1
      ],
      [
        1,
        1,
        1,
        1,
        1,
        1,
        1,
        1
      ],
      [
        1,
        1,
        1,
        1,
        1,
        1,
        1,
        1
      ],
      [
        1,
        1,
        1,
        1,
        1,
        1,
        1,
        1
      ],
      [
        1,
        1,
        1,
        1,
        1,
        1,
        1,
        1
      ],
      [
        1,
        1,
        1,
        1,
        1,
        1,
        1,
        1
      ],
      [
        1,
        1,
        1,
        1,
        1,
        1,
        1,
        1
      ],
      [
        1,
        1,
        1,
        1,
        1,
        1,
        1,
        1
      ],
      [
        1,
        1,
        1,
        1,
        1,
        1,
        1,
        1
      ],
      [
        1,
        1,
        1,
        1,
        1,
        1,
        1,
        1
      ],
      [
        1,
        1,
        1,
        1,
        1,
        1,
        1,
        1
      ],
      [
        1,
        1,
        1,
        1,
        1,
        1,
        1,
        1
      ]
    ],
    "_output_item": "Objective function: 1432 + 11462 = 12894 \nStart Times: [0, 266, 844, 403, 607, 310, 925, 153, 134, 491, 165, 45, 253, 855, 700, 620, 99, 1011, 76, 1114, 829, 246, 362, 395, 1360, 784, 1155, 882, 970, 1053, 1257, 1186, 902, 442, 306, 1209, 1280, 176, 944, 491, 1114, 742, 245, 1065, 375, 836, 1152, 945, 752, 1328, 98, 221, 351, 157, 257, 52, 1152, 1360, 1009, 133, 885, 403, 534, 0, 449, 378, 764, 869, 548, 0, 1100, 700, 1065, 630, 149, 796, 0, 1306, 999, 1288, 221, 0, 436, 151, 1259, 482, 326, 1160, 690, 1403, 925, 1341, 758, 1144, 1180, 1048, 417, 93, 1092, 947, 223, 730, 484, 534, 149, 1162, 1348, 0, 60, 1198, 395, 720, 1285, 575, 1187, 1360, 1035, 630, 246, 969, 621, 1202, 1283, 731, 1180, 694, 855, 792, 988, 310, 566, 460, 668, 945, 796, 855, 820, 1089, 474, 524, 149, 20, 223, 1342, 944, 1263, 1166, 616, 1350, 421, 172, 1144, 1180, 938, 690, 252, 1083, 1339, 988, 1006, 546, 1238, 634, 779, 1202, 825, 1351, 1306, 376, 845, 493, 1053, 583, 988, 631, 1257, 282, 677, 378, 1224, 473, 565, 751, 125, 1259, 172, 0, 1287, 1229, 125, 157, 76]\nSpeed Scaling; [1, 1, 1, 1, 1, 1, 1, 1, 1, 1, 1, 1, 1, 1, 1, 1, 1, 1, 1, 1, 1, 1, 1, 1, 1, 1, 1, 1, 1, 1, 1, 1, 1, 1, 1, 1, 1, 1, 1, 1, 1, 1, 1, 1, 1, 1, 1, 1, 1, 1, 1, 1, 1, 1, 1, 1, 1, 1, 1, 1, 1, 1, 1, 1, 1, 1, 1, 1, 1, 1, 1, 1, 1, 1, 1, 1, 1, 1, 1, 1, 1, 1, 1, 1, 1, 1, 1, 1, 1, 1, 1, 1, 1, 1, 1, 1, 1, 1, 1, 1, 1, 1, 1, 1, 1, 1, 1, 1, 1, 1, 1, 1, 1, 1, 1, 1, 1, 1, 1, 1, 1, 1, 1, 1, 1, 1, 1, 1, 1, 1, 1, 1, 1, 1, 1, 1, 1, 1, 1, 1, 1, 1, 1, 1, 1, 1, 1, 1, 1, 1, 1, 1, 1, 1, 1, 1, 1, 1, 1, 1, 1, 1, 1, 1, 1, 1, 1, 1, 1, 1, 1, 1, 1, 1, 1, 1, 1, 1, 1, 1, 1, 1, 1, 1, 1, 1, 1, 1, 1, 1, 1, 1]\n",
    "_checker": ""
  },
  "statistics": {
    "paths": 0,
    "flatBoolVars": 4416,
    "flatIntVars": 386,
    "flatBoolConstraints": 2208,
    "flatIntConstraints": 5282,
    "evaluatedHalfReifiedConstraints": 4416,
    "method": "minimize",
    "flatTime": 171.97799999999998,
    "objective": 12894,
    "objectiveBound": 12088,
    "boolVariables": 4529,
    "failures": 783,
    "propagations": 1547243,
    "solveTime": 1343.8300000000002,
    "time": 1631.0,
    "nSolutions": 161,
    "maxTime": 96272,
    "makespan": 1432.0,
    "energy": 11462.0
  }
}