{
  "status": "OPTIMAL_SOLUTION",
  "solution": {
    "objective": 12383,
    "start_time": [
      [
        1630,
        97,
        334,
        1192,
        1457,
        237,
        527,
        981,
        1126,
        2180,
        1527,
        808,
        789,
        953,
        1102,
        169,
        1576,
        1841,
        265,
        1168,
        1262,
        2241,
        1608,
        1019,
        1414,
        2097,
        316,
        1948,
        1892,
        548,
        645,
        0,
        2033,
        451,
        773,
        738,
        1046,
        1066,
        296,
        1910,
        906
      ],
      [
        2379,
        1098,
        1356,
        1653,
        2110,
        2394,
        1037,
        251,
        2341,
        1583,
        1906,
        2167,
        753,
        2412,
        1766,
        2330,
        606,
        1720,
        1512,
        1686,
        1828,
        1416,
        789,
        190,
        690,
        1295,
        1927,
        23,
        2060,
        951,
        118,
        1170,
        523,
        406,
        1206,
        344,
        2241,
        451,
        821,
        896,
        1964
      ],
      [
        220,
        1020,
        1486,
        852,
        1168,
        951,
        1841,
        2227,
        2379,
        24,
        287,
        523,
        1089,
        2292,
        128,
        2038,
        2179,
        1751,
        1279,
        803,
        1611,
        46,
        2106,
        504,
        1322,
        1964,
        405,
        0,
        863,
        196,
        738,
        1068,
        606,
        323,
        1550,
        692,
        1152,
        1414,
        1701,
        1205,
        1877
      ],
      [
        511,
        2072,
        1042,
        2159,
        1797,
        265,
        1332,
        480,
        453,
        1321,
        1692,
        1558,
        1211,
        26,
        305,
        1309,
        1773,
        1085,
        1150,
        1252,
        2201,
        128,
        653,
        868,
        378,
        931,
        608,
        1588,
        0,
        711,
        1616,
        193,
        969,
        1053,
        290,
        805,
        1872,
        1486,
        999,
        1283,
        2060
      ]
    ],
    "SpeedScaling": [
      [
        1,
        1,
        1,
        1,
        1,
        1,
        1,
        1,
        1,
        1,
        1,
        1,
        1,
        1,
        1,
        1,
        1,
        1,
        1,
        1,
        1,
        1,
        1,
        1,
        1,
        1,
        1,
        1,
        1,
        1,
        1,
        1,
        1,
        1,
        1,
        1,
        1,
        1,
        1,
        1,
        1
      ],
      [
        1,
        1,
        1,
        1,
        1,
        1,
        1,
        1,
        1,
        1,
        1,
        1,
        1,
        1,
        1,
        1,
        1,
        1,
        1,
        1,
        1,
        1,
        1,
        1,
        1,
        1,
        1,
        1,
        1,
        1,
        1,
        1,
        1,
        1,
        1,
        1,
        1,
        1,
        1,
        1,
        1
      ],
      [
        1,
        1,
        1,
        1,
        1,
        1,
        1,
        1,
        1,
        1,
        1,
        1,
        1,
        1,
        1,
        1,
        1,
        1,
        1,
        1,
        1,
        1,
        1,
        1,
        1,
        1,
        1,
        1,
        1,
        1,
        1,
        1,
        1,
        1,
        1,
        1,
        1,
        1,
        1,
        1,
        1
      ],
      [
        1,
        1,
        1,
        1,
        1,
        1,
        1,
        1,
        1,
        1,
        1,
        1,
        1,
        1,
        1,
        1,
        1,
        1,
        1,
        1,
        1,
        1,
        1,
        1,
        1,
        1,
        1,
        1,
        1,
        1,
        1,
        1,
        1,
        1,
        1,
        1,
        1,
        1,
        1,
        1,
        1
      ]
    ],
    "_output_item": "Objective function: 2438 + 9945 = 12383 \nStart Times: [1630, 97, 334, 1192, 1457, 237, 527, 981, 1126, 2180, 1527, 808, 789, 953, 1102, 169, 1576, 1841, 265, 1168, 1262, 2241, 1608, 1019, 1414, 2097, 316, 1948, 1892, 548, 645, 0, 2033, 451, 773, 738, 1046, 1066, 296, 1910, 906, 2379, 1098, 1356, 1653, 2110, 2394, 1037, 251, 2341, 1583, 1906, 2167, 753, 2412, 1766, 2330, 606, 1720, 1512, 1686, 1828, 1416, 789, 190, 690, 1295, 1927, 23, 2060, 951, 118, 1170, 523, 406, 1206, 344, 2241, 451, 821, 896, 1964, 220, 1020, 1486, 852, 1168, 951, 1841, 2227, 2379, 24, 287, 523, 1089, 2292, 128, 2038, 2179, 1751, 1279, 803, 1611, 46, 2106, 504, 1322, 1964, 405, 0, 863, 196, 738, 1068, 606, 323, 1550, 692, 1152, 1414, 1701, 1205, 1877, 511, 2072, 1042, 2159, 1797, 265, 1332, 480, 453, 1321, 1692, 1558, 1211, 26, 305, 1309, 1773, 1085, 1150, 1252, 2201, 128, 653, 868, 378, 931, 608, 1588, 0, 711, 1616, 193, 969, 1053, 290, 805, 1872, 1486, 999, 1283, 2060]\nSpeed Scaling; [1, 1, 1, 1, 1, 1, 1, 1, 1, 1, 1, 1, 1, 1, 1, 1, 1, 1, 1, 1, 1, 1, 1, 1, 1, 1, 1, 1, 1, 1, 1, 1, 1, 1, 1, 1, 1, 1, 1, 1, 1, 1, 1, 1, 1, 1, 1, 1, 1, 1, 1, 1, 1, 1, 1, 1, 1, 1, 1, 1, 1, 1, 1, 1, 1, 1, 1, 1, 1, 1, 1, 1, 1, 1, 1, 1, 1, 1, 1, 1, 1, 1, 1, 1, 1, 1, 1, 1, 1, 1, 1, 1, 1, 1, 1, 1, 1, 1, 1, 1, 1, 1, 1, 1, 1, 1, 1, 1, 1, 1, 1, 1, 1, 1, 1, 1, 1, 1, 1, 1, 1, 1, 1, 1, 1, 1, 1, 1, 1, 1, 1, 1, 1, 1, 1, 1, 1, 1, 1, 1, 1, 1, 1, 1, 1, 1, 1, 1, 1, 1, 1, 1, 1, 1, 1, 1, 1, 1, 1, 1, 1, 1, 1, 1]\n",
    "_checker": ""
  },
  "statistics": {
    "paths": 0,
    "flatBoolVars": 492,
    "flatIntVars": 330,
    "flatBoolConstraints": 246,
    "flatIntConstraints": 3938,
    "evaluatedHalfReifiedConstraints": 492,
    "method": "minimize",
    "flatTime": 115.125,
    "objective": 12383,
    "objectiveBound": 12383,
    "boolVariables": 246,
    "failures": 0,
    "propagations": 104989,
    "solveTime": 368.362,
    "time": 528.0,
    "nSolutions": 47,
    "maxTime": 135220,
    "makespan": 2438.0,
    "energy": 9945.0
  }
}